ip_scanner/__init__.py
scyrpt_studio_ip_scanner-0.0.4.dist-info/LICENSE
scyrpt_studio_ip_scanner-0.0.4.dist-info/METADATA
scyrpt_studio_ip_scanner-0.0.4.dist-info/WHEEL
scyrpt_studio_ip_scanner-0.0.4.dist-info/entry_points.txt
scyrpt_studio_ip_scanner-0.0.4.dist-info/top_level.txt
scyrpt_studio_ip_scanner-0.0.4.dist-info/RECORD
