Metadata-Version: 2.1
Name: scyrpt-studio-ip-scanner
Version: 0.0.4
Summary: Pip package to scan IP address on local ip range.
Author-email: Rishabh Wadhwa <rishabh0206@gmail.com>
License: MIT License        
Project-URL: Homepage, https://github.com/rishabh0206/ip-scanner
Keywords: ip,scanner
Classifier: License :: OSI Approved :: MIT License
Classifier: Programming Language :: Python
Classifier: Programming Language :: Python :: 3
Requires-Python: >=3.8
License-File: LICENSE
Provides-Extra: dev
Requires-Dist: black ; extra == 'dev'
Requires-Dist: bumpversion ; extra == 'dev'
Requires-Dist: isort ; extra == 'dev'
Requires-Dist: pip-tools ; extra == 'dev'
Requires-Dist: pytest ; extra == 'dev'
